jsoncut/__init__.py
jsoncut/cli.py
jsoncut/core.py
jsoncut/exceptions.py
jsoncut/highlighter.py
jsoncut/inspector.py
jsoncut/sequencer.py
jsoncut/tokenizer.py
jsoncut/treecrawler.py
jsoncut-0.6.dist-info/DESCRIPTION.rst
jsoncut-0.6.dist-info/METADATA
jsoncut-0.6.dist-info/RECORD
jsoncut-0.6.dist-info/WHEEL
jsoncut-0.6.dist-info/entry_points.txt
jsoncut-0.6.dist-info/metadata.json
jsoncut-0.6.dist-info/top_level.txt
