Metadata-Version: 2.0
Name: jsoncut
Version: 0.6
Summary: A JSON inspection & pruning tool.
Home-page: http://github.com/bpeterso2000/jsoncut
Author: Brian Peterson
Author-email: bpeterso2000@yahoo.com
License: UNKNOWN
Platform: UNKNOWN
Classifier: License :: OSI Approved :: MIT License
Classifier: Programming Language :: Python
Classifier: Programming Language :: Python :: 3
Requires-Dist: click
Requires-Dist: colorama
Requires-Dist: pygments
